hjpencias/PiedraPapelTijeras.py
hjpencias/TresEnRaya.py
hjpencias/Wordle.py
hjpencias/__init__.py
hjpencias-0.2.0.dist-info/METADATA
hjpencias-0.2.0.dist-info/WHEEL
hjpencias-0.2.0.dist-info/top_level.txt
hjpencias-0.2.0.dist-info/RECORD
