Metadata-Version: 2.1
Name: hjpencias
Version: 0.2.0
Summary: libreria de juegos ligeros y sencillos de python
Home-page: https://trabajodepanas.com
Author: Héctor Jiménez
Author-email: hectorjjmch@gmail.com
License: Copyright
Requires-Dist: colorama
